Metadata-Version: 2.1
Name: iac-inscript
Version: 1.0.1
Summary: python代码一键加密
Home-page: https://github.com/Khalil12138/iac-inscript.git
Author: Boris
Author-email: boris@bzkj.tech
License: MIT
Classifier: Programming Language :: Python :: 3
License-File: LICENSE
Requires-Dist: Cython==3.0.10
